docflow/__init__.py
docflow/cli.py
docflow/context.py
docflow/docbasket.py
docflow/docflow.py
docflow/document.py
docflow/config/__init__.py
docflow/config/config_manager.py
docflow/config/default_config.yaml
docflow/config/docflow_config.py
docflow/db/__init__.py
docflow/db/abstract_database.py
docflow/db/connection.py
docflow/db/database_factory.py
docflow/db/models.py
docflow/db/postgres_database.py
docflow/db/repository.py
docflow/db/sqlite_database.py
docflow/models/__init__.py
docflow/models/document_metadata.py
docflow/models/metadata_keys.py
docflow/processors/__init__.py
docflow/processors/base.py
docflow/processors/csv_to_json.py
docflow/processors/factory.py
docflow/processors/mapper.py
docflow/processors/models.py
docflow/processors/pdf_invoice.py
docflow/processors/pdf_to_text.py
docflow/services/__init__.py
docflow/services/docbasket_service.py
docflow/services/document_service.py
docflow/services/metadata_service.py
docflow/services/storage_service.py
docflow/storage/__init__.py
docflow/storage/abstract_storage.py
docflow/storage/filesystem_storage.py
docflow/storage/s3_storage.py
docflow/storage/storage_factory.py
docflow/transport/__init__.py
docflow/transport/base.py
docflow/transport/config.py
docflow/transport/http.py
docflow/transport/local.py
docflow/transport/models.py
docflow/transport/repository.py
docflow/transport/route.py
docflow/transport/route_mapper.py
docflow/transport/sftp.py
docflow/transport/transport_result.py
docflow/transport/transporter_factory.py
docflow/utils/__init__.py
docflow/utils/file_utils.py
pydocflow-0.1.9.dist-info/licenses/LICENSE
tests/__init__.py
tests/test_db_connection.py
tests/test_docbasket.py
tests/test_docflow.py
tests/test_docflow_postgres.py
tests/test_docflow_usage.py
tests/test_route.py
tests/test_route_management.py
tests/test_simple.py
tests/test_sqlite.py
tests/test_transport_base.py
tests/test_transport_integration.py
tests/test_transport_postgres.py
tests/test_transport_sqlite.py
tests/test_transport_workflow.py
tests/verify_routes.py
pydocflow-0.1.9.dist-info/METADATA
pydocflow-0.1.9.dist-info/WHEEL
pydocflow-0.1.9.dist-info/entry_points.txt
pydocflow-0.1.9.dist-info/top_level.txt
pydocflow-0.1.9.dist-info/RECORD
