Metadata-Version: 2.4
Name: PyDocflow
Version: 0.1.9
Summary: A robust, lightweight, and developer-friendly document management and transport system for Python.
Home-page: https://github.com/tommyGPT2S/DocFlow
Author: Tommy Jiang
Author-email: Tommy Jiang <tommyscosc@scos.ai>
License: MIT License
Requires-Python: >=3.8
License-File: LICENSE
Requires-Dist: sqlalchemy>=2.0.0
Requires-Dist: psycopg2-binary>=2.9.0
Requires-Dist: pyyaml>=6.0.0
Requires-Dist: pytest>=7.0.0
Requires-Dist: boto3>=1.26.0
Requires-Dist: pydantic>=2.0.0
Requires-Dist: paramiko>=3.4.0
Requires-Dist: aiohttp>=3.9.0
Requires-Dist: python-dotenv>=1.0.0
Requires-Dist: click>=8.0.0
Dynamic: author
Dynamic: home-page
Dynamic: license-file
Dynamic: requires-python
